shamboflow/__init__.py
shamboflow/callbacks.py
shamboflow/layers.py
shamboflow/models.py
shamboflow/engine/__init__.py
shamboflow/engine/activations.py
shamboflow/engine/base_callback.py
shamboflow/engine/base_layers.py
shamboflow/engine/base_models.py
shamboflow/engine/d_activations.py
shamboflow/engine/d_losses.py
shamboflow/engine/losses.py
shamboflow-1.0.2.1.dist-info/LICENSE
shamboflow-1.0.2.1.dist-info/METADATA
shamboflow-1.0.2.1.dist-info/WHEEL
shamboflow-1.0.2.1.dist-info/top_level.txt
shamboflow-1.0.2.1.dist-info/RECORD
