Metadata-Version: 2.1
Name: shamboflow
Version: 1.0.2.1
Summary: A fierce Tensorflow competitor
Home-page: https://github.com/ShambaC/shamboflow
Author: ShambaC
Author-email: shambachowdhury2@gmail.com
Project-URL: Bug Tracker, https://github.com/ShambaC/shamboflow/issues
Project-URL: Source Code, https://github.com/ShambaC/shamboflow
Classifier: Programming Language :: Python :: 3
Classifier: License :: OSI Approved :: MIT License
Classifier: Operating System :: OS Independent
Requires-Python: >=3.9
License-File: LICENSE
Requires-Dist: colorama
Requires-Dist: cupy-cuda12x
Requires-Dist: numpy
Requires-Dist: tqdm
